[
    {
        "name": "Commuting",
        "img": "commuting.png",
        "subtopics": ["Driving", "Public Transportation", "Snow Clearing"],
        "data": "commuting.json"
    },
    {
        "name": "Equipment",
        "img": "equipment.png",
        "subtopics": ["Snow Shovel", "Ice Scraper", "Snow Blower"],
        "data": "equipment.json"
    },
    {
        "name": "Activities",
        "img": "activities.png",
        "subtopics": ["Skiing", "Snowboarding", "Sledding", "Snowball Fights", "Building a Snowman"],
        "data": "activities.json"
    }
]